cgcomponents/exceptions.py
cgcomponents/logs.py
cgcomponents/requests_cg.py
portalcomponentscg/const.py
portalcomponentscg/exceptions.py
portalcomponentscg/logs.py
portalcomponentscg/requests_cg.py
cgcomponents-2.0.4.dist-info/LICENSE
cgcomponents-2.0.4.dist-info/METADATA
cgcomponents-2.0.4.dist-info/WHEEL
cgcomponents-2.0.4.dist-info/top_level.txt
cgcomponents-2.0.4.dist-info/RECORD
