Metadata-Version: 2.1
Name: cgcomponents
Version: 2.0.4
Summary: Components para scrapping da CG.
Home-page: https://github.com/ramirooliveiracg/cgcomponents
Author: Gabriel Dalacorte e Rogerio Filho
Author-email: gnunes.servico@gmail.com, crofilho2@gmail.com
License: MIT
Classifier: License :: OSI Approved :: MIT License
Classifier: Programming Language :: Python :: 3
Classifier: Programming Language :: Python :: 3.7
License-File: LICENSE
Requires-Dist: requests
Requires-Dist: Unidecode
